Workbook

Sheet README
A1: THE UNLOX ACADEMY - DA/DS TRACK
A2: Excel Minor Project - Sales Operations Analytics
A3: Interview-Grade Data Analytics Assessment · 100 Marks
A5: THE SCENARIO
A6: You have just joined the analytics team at a fast-growing multi-category retailer operating across 6 Indian cities.
A7: The head of sales has handed you 5 raw data files - Orders, Customers, Products, Sales Reps, and Targets - and asked
A8: you to answer a set of business questions before the leadership review tomorrow morning.
A10: The data is REAL-WORLD messy: duplicates, missing references, inconsistent case, invalid records, discontinued SKUs.
A11: Part of the assessment is spotting and handling these issues correctly. A wrong-looking answer isn't always wrong -
A12: sometimes the data itself is telling a story.
A14: RULES OF THE ASSESSMENT
A15: 1. Write your answer in the YELLOW cells on each question sheet. Empty answer cell = 0 marks.
... A22: MARKS DISTRIBUTION
A23: Section | B23: Topic | C23: Questions | D23: Marks
A24: Q1 | B24: Lookup Functions (VLOOKUP, INDEX-MATCH, chained lookups) | C24: 8 | D24: 25
A25: Q2 | B25: Data Cleaning & Quality Diagnostics | C25: 6 | D25: 20
A26: Q3 | B26: Conditional Aggregation (SUMIFS, COUNTIFS, IF logic) | C26: 6 | D26: 25
A27: Q4 | B27: Pivot Tables (2D pivots, % of total, calculated fields) | C27: 5 | D27: 20
A28: Q5 | B28: Advanced (Ranking, Running Totals, Multi-condition) | C28: 5 | D28: 10
B29: TOTAL | C29: 30 | D29: 100
A32: PERFORMANCE TIERS
A33: Marks | B33: Tier | C33: Interview Verdict
A34: 85 - 100 | B34: Excellent | C34: Round 1 clear - Excel not a concern
A35: 70 - 84 | B35: Good | C35: Round 1 clear with minor gaps
A36: 55 - 69 | B36: Borderline | C36: Round 1 uncertain - needs revision
A37: 40 - 54 | B37: Weak | C37: Round 1 likely reject - 2 weeks of practice needed
A38: < 40 | B38: Insufficient | C38: Round 1 reject - foundational gaps
A41: DATA SHEETS OVERVIEW
A42: Sheet | B42: Rows | C42: Key Columns | D42: Joins to
A43: Orders | B43: ~2000 | C43: order_id, order_date, customer_id, product_id, sales_rep_id, quantity, unit_price, discount_pct, final_amount, payment_status, ship_city | D43: All others
A44: Customers | B44: 300 | C44: customer_id (PK), customer_name, age, city, segment, signup_date | D44: Orders via customer_id
A45: Products | B45: 60 | C45: product_id (PK), product_name, category, unit_cost, unit_price, is_active | D45: Orders via product_id
A46: Sales_Reps | B46: 30 | C46: rep_id (PK), rep_name, region, hire_date, team_lead_id | D46: Orders via sales_rep_id, self-join via team_lead_id
A47: Targets | B47: 30 × 12 | C47: rep_id (PK), Jan-24 through Dec-24 monthly target values | D47: Sales_Reps via rep_id

Sheet Detail1
A1: Details for Sum of final_amount - Region: East (+)
A3: order_id | B3: order_date | C3: customer_id | D3: product_id | E3: sales_rep_id | F3: quantity | G3: unit_price | H3: discount_pct | I3: final_amount | J3: payment_status | K3: ship_city | L3: Clean City | M3: Category | N3: Region | O3: Unit Cost | P3: Unit Price
A4: ORD-00001 | B4: 45549 | C4: CUST-0243 | D4: PROD-014 | E4: R007 | F4: 8 | G4: 3620 | H4: 15.4 | I4: 24500.16 | J4: Completed | K4: Pune | L4: Pune | M4: Apparel | N4: North | O4: 2509 | P4: 3620
A5: ORD-00002 | B5: 45340 | C5: CUST-0202 | D5: PROD-020 | E5: R005 | F5: 2 | G5: 820 | H5: 10.8 | I5: 1462.88 | J5: Pending | K5: Chennai | L5: Chennai | M5: Apparel | N5: North | O5: 391 | P5: 820
A6: ORD-00005 | B6: 45611 | C6: CUST-0180 | D6: PROD-012 | E6: R008 | F6: 1 | G6: 3160 | H6: 26 | I6: 2338.4 | J6: Completed | K6: Chennai | L6: Chennai | M6: Apparel | N6: North | O6: 1886 | P6: 3160
A7: ORD-00021 | B7: 45470 | C7: CUST-0159 | D7: PROD-019 | E7: R006 | F7: 7 | G7: 2480 | H7: 28.7 | I7: 12377.68 | J7: Completed | K7: Hyderabad | L7: Hyderabad | M7: Apparel | N7: North | O7: 1173 | P7: 2480
A8: ORD-00023 | B8: 45530 | C8: CUST-0107 | D8: PROD-015 | E8: R030 | F8: 9 | G8: 2720 | H8: 26.2 | I8: 18066.24 | J8: Completed | K8: Pune | L8: Pune | M8: Apparel | N8: West | O8: 1962 | P8: 2720
A9: ORD-00045 | B9: 45373 | C9: CUST-0152 | D9: PROD-019 | E9: R019 | F9: 2 | G9: 2480 | H9: 17.3 | I9: 4101.92 | J9: Completed | K9: Bengaluru | L9: Bengaluru | M9: Apparel | N9: East | O9: 1173 | P9: 2480
A10: ORD-00047 | B10: 45340 | C10: CUST-0112 | D10: PROD-013 | E10: R017 | F10: 4 | G10: 3640 | H10: 20.7 | I10: 11546.08 | J10: Completed | K10: Hyderabad | L10: Hyderabad | M10: Apparel | N10: East | O10: 2611 | P10: 3640
A11: ORD-00055 | B11: 45515 | C11: CUST-0267 | D11: PROD-013 | E11: R007 | F11: 4 | G11: 3640 | H11: 9.9 | I11: 13118.56 | J11: Refunded | K11: Hyderabad | L11: Hyderabad | M11: Apparel | N11: North | O11: 2611 | P11: 3640
A12: ORD-00066 | B12: 45462 | C12: CUST-0283 | D12: PROD-020 | E12: R020 | F12: 8 | G12: 820 | H12: 24 | I12: 4985.6 | J12: Completed | K12: Delhi | L12: Delhi | M12: Apparel | N12: East | O12: 391 | P12: 820
A13: ORD-00068 | B13: 45328 | C13: CUST-0161 | D13: PROD-014 | E13: R017 | F13: 2 | G13: 3620 | H13: 19.1 | I13: 5857.16 | J13: Completed | K13: Chennai | L13: Chennai | M13: Apparel | N13: East | O13: 2509 | P13: 3620
A14: ORD-00069 | B14: 45459 | C14: CUST-0033 | D14: PROD-016 | E14: R025 | F14: 1 | G14: 620 | H14: 1 | I14: 613.8 | J14: Completed | K14: Delhi | L14: Delhi | M14: Apparel | N14: West | O14: 396 | P14: 620
A15: ORD-00071 | B15: 45470 | C15: CUST-0180 | D15: PROD-012 | E15: R002 | F15: 10 | G15: 3160 | H15: 15.8 | I15: 26607.2 | J15: Completed | K15: Chennai | L15: Chennai | M15: Apparel | N15: North | O15: 1886 | P15: 3160
... A2003: ORD-01999 | B2003: 45370 | C2003: CUST-0167 | D2003: PROD-052 | E2003: R008 | F2003: 6 | G2003: 5410 | H2003: 15.5 | I2003: 27428.7 | J2003: Completed | K2003: Delhi | L2003: Delhi | M2003: Sports | N2003: South | O2003: 2265 | P2003: 5410

Sheet Sheet1
A1: Clean City | B1: Delhi
A3: Row Labels | B3: Sum of final_amount | C3: Average of profit_margin
A4: 45294 | B4: 25888.2 | C4: 1.1433755
A5: 45298 | B5: 5178.24 | C5: 0.64577203
A6: 45301 | B6: 3024.56 | C6: 1.2613521
A7: 45306 | B7: 4135.86 | C7: 0.54919226
A8: 45309 | B8: 8266.56 | C8: 0.87697648
A9: 45310 | B9: 19726.2 | C9: 1.2950997
A10: 45312 | B10: 18682.1 | C10: 0.82218024
A11: 45313 | B11: 21390.08 | C11: 0.606186
A12: 45316 | B12: 10014.62 | C12: 1.2613521
A13: 45318 | B13: 25722.48 | C13: 1.0429195
A14: 45322 | B14: 10201.62 | C14: 1.1937249
A15: 45325 | B15: 26704.12 | C15: 1.0549141
... A207: 45656 | B207: 7160.36 | C207: 0.66759195
A208: Grand Total | B208: 3905749.7 | C208: 1

Sheet Orders
A1: order_id | B1: order_date | C1: customer_id | D1: product_id | E1: sales_rep_id | F1: quantity | G1: unit_price | H1: discount_pct | I1: final_amount | J1: payment_status | K1: ship_city | L1: Clean City | M1: Category | N1: Region | O1: Unit Cost | P1: Unit Price
A2: ORD-00001 | B2: 45549 | C2: CUST-0243 | D2: PROD-014 | E2: R007 | F2: 8 | G2: 3620 | H2: 15.4 | I2: 24500.16 | J2: Completed | K2: Pune | L2: =PROPER(TRIM(K2)) -> Pune | M2: =_xlfn.XLOOKUP(D2, Products!A:A, Products!C:C) -> Apparel | N2: =_xlfn.XLOOKUP(E2, Sales_Reps!A:A, Sales_Reps!C:C) -> North | O2: =_xlfn.XLOOKUP(D2, Products!A:A, Products!D:D) -> 2509 | P2: =_xlfn.XLOOKUP(D2, Products!A:A, Products!E:E) -> 3620
A3: ORD-00002 | B3: 45340 | C3: CUST-0202 | D3: PROD-020 | E3: R005 | F3: 2 | G3: 820 | H3: 10.8 | I3: 1462.88 | J3: Pending | K3: Chennai | L3: =PROPER(TRIM(K3)) -> Chennai | M3: =_xlfn.XLOOKUP(D3, Products!A:A, Products!C:C) -> Apparel | N3: =_xlfn.XLOOKUP(E3, Sales_Reps!A:A, Sales_Reps!C:C) -> North | O3: =_xlfn.XLOOKUP(D3, Products!A:A, Products!D:D) -> 391 | P3: =_xlfn.XLOOKUP(D3, Products!A:A, Products!E:E) -> 820
A4: ORD-00003 | B4: 45371 | C4: CUST-0098 | D4: PROD-053 | E4: R014 | F4: 8 | G4: 470 | H4: 3.3 | I4: 3635.92 | J4: Pending | K4: Delhi | L4: =PROPER(TRIM(K4)) -> Delhi | M4: =_xlfn.XLOOKUP(D4, Products!A:A, Products!C:C) -> Sports | N4: =_xlfn.XLOOKUP(E4, Sales_Reps!A:A, Sales_Reps!C:C) -> South | O4: =_xlfn.XLOOKUP(D4, Products!A:A, Products!D:D) -> 302 | P4: =_xlfn.XLOOKUP(D4, Products!A:A, Products!E:E) -> 470
A5: ORD-00004 | B5: 45413 | C5: CUST-0071 | D5: PROD-028 | E5: R006 | F5: 1 | G5: 3660 | H5: 15.7 | I5: 3085.38 | J5: Completed | K5: Delhi | L5: =PROPER(TRIM(K5)) -> Delhi | M5: =_xlfn.XLOOKUP(D5, Products!A:A, Products!C:C) -> Grocery | N5: =_xlfn.XLOOKUP(E5, Sales_Reps!A:A, Sales_Reps!C:C) -> North | O5: =_xlfn.XLOOKUP(D5, Products!A:A, Products!D:D) -> 2214 | P5: =_xlfn.XLOOKUP(D5, Products!A:A, Products!E:E) -> 3660
A6: ORD-00005 | B6: 45611 | C6: CUST-0180 | D6: PROD-012 | E6: R008 | F6: 1 | G6: 3160 | H6: 26 | I6: 2338.4 | J6: Completed | K6: Chennai | L6: =PROPER(TRIM(K6)) -> Chennai | M6: =_xlfn.XLOOKUP(D6, Products!A:A, Products!C:C) -> Apparel | N6: =_xlfn.XLOOKUP(E6, Sales_Reps!A:A, Sales_Reps!C:C) -> North | O6: =_xlfn.XLOOKUP(D6, Products!A:A, Products!D:D) -> 1886 | P6: =_xlfn.XLOOKUP(D6, Products!A:A, Products!E:E) -> 3160
A7: ORD-00006 | B7: 45406 | C7: CUST-0275 | D7: PROD-032 | E7: R025 | F7: 4 | G7: 370 | H7: 29 | I7: 1050.8 | J7: Completed | K7: Mumbai | L7: =PROPER(TRIM(K7)) -> Mumbai | M7: =_xlfn.XLOOKUP(D7, Products!A:A, Products!C:C) -> Home | N7: =_xlfn.XLOOKUP(E7, Sales_Reps!A:A, Sales_Reps!C:C) -> West | O7: =_xlfn.XLOOKUP(D7, Products!A:A, Products!D:D) -> 288 | P7: =_xlfn.XLOOKUP(D7, Products!A:A, Products!E:E) -> 370
A8: ORD-00007 | B8: 45455 | C8: CUST-0293 | D8: PROD-057 | E8: R024 | F8: 3 | G8: 960 | H8: 5.8 | I8: 2712.96 | J8: Completed | K8: Bengaluru | L8: =PROPER(TRIM(K8)) -> Bengaluru | M8: =_xlfn.XLOOKUP(D8, Products!A:A, Products!C:C) -> Sports | N8: =_xlfn.XLOOKUP(E8, Sales_Reps!A:A, Sales_Reps!C:C) -> West | O8: =_xlfn.XLOOKUP(D8, Products!A:A, Products!D:D) -> 705 | P8: =_xlfn.XLOOKUP(D8, Products!A:A, Products!E:E) -> 960
A9: ORD-00008 | B9: 45617 | C9: CUST-0281 | D9: PROD-007 | E9: R019 | F9: 8 | G9: 1430 | H9: 2.4 | I9: 11165.44 | J9: Completed | K9: Bengaluru | L9: =PROPER(TRIM(K9)) -> Bengaluru | M9: =_xlfn.XLOOKUP(D9, Products!A:A, Products!C:C) -> Electronics | N9: =_xlfn.XLOOKUP(E9, Sales_Reps!A:A, Sales_Reps!C:C) -> East | O9: =_xlfn.XLOOKUP(D9, Products!A:A, Products!D:D) -> 861 | P9: =_xlfn.XLOOKUP(D9, Products!A:A, Products!E:E) -> 1430
A10: ORD-00009 | B10: 45549 | C10: CUST-0260 | D10: PROD-038 | E10: R008 | F10: 3 | G10: 5490 | H10: 14.2 | I10: 14131.26 | J10: Completed | K10: Bengaluru | L10: =PROPER(TRIM(K10)) -> Bengaluru | M10: =_xlfn.XLOOKUP(D10, Products!A:A, Products!C:C) -> Home | N10: =_xlfn.XLOOKUP(E10, Sales_Reps!A:A, Sales_Reps!C:C) -> North | O10: =_xlfn.XLOOKUP(D10, Products!A:A, Products!D:D) -> 2549 | P10: =_xlfn.XLOOKUP(D10, Products!A:A, Products!E:E) -> 5490
A11: ORD-00010 | B11: 45396 | C11: CUST-0147 | D11: PROD-030 | E11: R028 | F11: 3 | G11: 970 | H11: 1.2 | I11: 2875.08 | J11: Completed | K11: Pune | L11: =PROPER(TRIM(K11)) -> Pune | M11: =_xlfn.XLOOKUP(D11, Products!A:A, Products!C:C) -> Grocery | N11: =_xlfn.XLOOKUP(E11, Sales_Reps!A:A, Sales_Reps!C:C) -> West | O11: =_xlfn.XLOOKUP(D11, Products!A:A, Products!D:D) -> 434 | P11: =_xlfn.XLOOKUP(D11, Products!A:A, Products!E:E) -> 970
A12: ORD-00011 | B12: 45560 | C12: CUST-0204 | D12: PROD-024 | E12: R010 | F12: 7 | G12: 2270 | H12: 7.1 | I12: 14761.81 | J12: Pending | K12: Hyderabad | L12: =PROPER(TRIM(K12)) -> Hyderabad | M12: =_xlfn.XLOOKUP(D12, Products!A:A, Products!C:C) -> Grocery | N12: =_xlfn.XLOOKUP(E12, Sales_Reps!A:A, Sales_Reps!C:C) -> South | O12: =_xlfn.XLOOKUP(D12, Products!A:A, Products!D:D) -> 1203 | P12: =_xlfn.XLOOKUP(D12, Products!A:A, Products!E:E) -> 2270
A13: ORD-00012 | B13: 45332 | C13: CUST-0147 | D13: PROD-010 | E13: R024 | F13: 9 | G13: 2640 | H13: 21.7 | I13: 18604.08 | J13: Completed | K13: Pune | L13: =PROPER(TRIM(K13)) -> Pune | M13: =_xlfn.XLOOKUP(D13, Products!A:A, Products!C:C) -> Electronics | N13: =_xlfn.XLOOKUP(E13, Sales_Reps!A:A, Sales_Reps!C:C) -> West | O13: =_xlfn.XLOOKUP(D13, Products!A:A, Products!D:D) -> 1149 | P13: =_xlfn.XLOOKUP(D13, Products!A:A, Products!E:E) -> 2640
... A1175: ORD-01174 | B1175: 45602 | C1175: CUST-0209 | D1175: PROD-026 | E1175: R029 | F1175: 8 | G1175: 4070 | H1175: 17.7 | I1175: 26796.88 | J1175: Completed | K1175: Pune | L1175: =PROPER(TRIM(K1175)) -> Pune | M1175: =_xlfn.XLOOKUP(D1175, Products!A:A, Products!C:C) -> Grocery | N1175: =_xlfn.XLOOKUP(E1175, Sales_Reps!A:A, Sales_Reps!C:C) -> West | O1175: =_xlfn.XLOOKUP(D1175, Products!A:A, Products!D:D) -> 2027 | P1175: =_xlfn.XLOOKUP(D1175, Products!A:A, Products!E:E) -> 4070
A1176: ORD-01175 | B1176: 45372 | C1176: CUST-0111 | D1176: PROD-041 | E1176: R005 | F1176: 1 | G1176: 1540 | H1176: 0.9 | I1176: 1526.14 | J1176: Completed | K1176: Chennai | L1176: =PROPER(TRIM(K1176)) -> Chennai | M1176: =_xlfn.XLOOKUP(D1176, Products!A:A, Products!C:C) -> Beauty | N1176: =_xlfn.XLOOKUP(E2, Sales_Reps!A:A, Sales_Reps!C:C) -> North | O1176: =_xlfn.XLOOKUP(D1176, Products!A:A, Products!D:D) -> 647 | P1176: =_xlfn.XLOOKUP(D1176, Products!A:A, Products!E:E) -> 1540
A1177: ORD-01176 | B1177: 45416 | C1177: CUST-0014 | D1177: PROD-048 | E1177: R024 | F1177: 10 | G1177: 5100 | H1177: 3 | I1177: 49470 | J1177: Completed | K1177: Bengaluru | L1177: =PROPER(TRIM(K1177)) -> Bengaluru | M1177: =_xlfn.XLOOKUP(D1177, Products!A:A, Products!C:C) -> Beauty | N1177: =_xlfn.XLOOKUP(E3, Sales_Reps!A:A, Sales_Reps!C:C) -> North | O1177: =_xlfn.XLOOKUP(D1177, Products!A:A, Products!D:D) -> 2237 | P1177: =_xlfn.XLOOKUP(D1177, Products!A:A, Products!E:E) -> 5100
A1178: ORD-01177 | B1178: 45656 | C1178: CUST-0073 | D1178: PROD-014 | E1178: R006 | F1178: 6 | G1178: 3620 | H1178: 20.2 | I1178: 17332.56 | J1178: Completed | K1178: Pune | L1178: =PROPER(TRIM(K1178)) -> Pune | M1178: =_xlfn.XLOOKUP(D1178, Products!A:A, Products!C:C) -> Apparel | N1178: =_xlfn.XLOOKUP(E4, Sales_Reps!A:A, Sales_Reps!C:C) -> South | O1178: =_xlfn.XLOOKUP(D1178, Products!A:A, Products!D:D) -> 2509 | P1178: =_xlfn.XLOOKUP(D1178, Products!A:A, Products!E:E) -> 3620
A1179: ORD-01178 | B1179: 45324 | C1179: CUST-0147 | D1179: PROD-046 | E1179: R003 | F1179: 7 | G1179: 4880 | H1179: 5 | I1179: 32452 | J1179: Completed | K1179: Pune | L1179: =PROPER(TRIM(K1179)) -> Pune | M1179: =_xlfn.XLOOKUP(D1179, Products!A:A, Products!C:C) -> Beauty | N1179: =_xlfn.XLOOKUP(E5, Sales_Reps!A:A, Sales_Reps!C:C) -> North | O1179: =_xlfn.XLOOKUP(D1179, Products!A:A, Products!D:D) -> 2768 | P1179: =_xlfn.XLOOKUP(D1179, Products!A:A, Products!E:E) -> 4880
A1180: ORD-01179 | B1180: 45472 | C1180: CUST-0006 | D1180: PROD-010 | E1180: R024 | F1180: 1 | G1180: 2640 | H1180: 4.1 | I1180: 2531.76 | J1180: Completed | K1180: Pune | L1180: =PROPER(TRIM(K1180)) -> Pune | M1180: =_xlfn.XLOOKUP(D1180, Products!A:A, Products!C:C) -> Electronics | N1180: =_xlfn.XLOOKUP(E6, Sales_Reps!A:A, Sales_Reps!C:C) -> North | O1180: =_xlfn.XLOOKUP(D1180, Products!A:A, Products!D:D) -> 1149 | P1180: =_xlfn.XLOOKUP(D1180, Products!A:A, Products!E:E) -> 2640
A1181: ORD-01180 | B1181: 45508 | C1181: CUST-0031 | D1181: PROD-026 | E1181: R020 | F1181: 9 | G1181: 4070 | H1181: 4.4 | I1181: 35018.28 | J1181: Completed | K1181: Hyderabad | L1181: =PROPER(TRIM(K1181)) -> Hyderabad | M1181: =_xlfn.XLOOKUP(D1181, Products!A:A, Products!C:C) -> Grocery | N1181: =_xlfn.XLOOKUP(E7, Sales_Reps!A:A, Sales_Reps!C:C) -> West | O1181: =_xlfn.XLOOKUP(D1181, Products!A:A, Products!D:D) -> 2027 | P1181: =_xlfn.XLOOKUP(D1181, Products!A:A, Products!E:E) -> 4070
A1182: ORD-01181 | B1182: 45617 | C1182: CUST-0084 | D1182: PROD-003 | E1182: R025 | F1182: 9 | G1182: 3570 | H1182: 24.8 | I1182: 24161.76 | J1182: Completed | K1182: Chennai | L1182: =PROPER(TRIM(K1182)) -> Chennai | M1182: =_xlfn.XLOOKUP(D1182, Products!A:A, Products!C:C) -> Electronics | N1182: =_xlfn.XLOOKUP(E8, Sales_Reps!A:A, Sales_Reps!C:C) -> West | O1182: =_xlfn.XLOOKUP(D1182, Products!A:A, Products!D:D) -> 1665 | P1182: =_xlfn.XLOOKUP(D1182, Products!A:A, Products!E:E) -> 3570
A1183: ORD-01182 | B1183: 45470 | C1183: CUST-0203 | D1183: PROD-043 | E1183: R005 | F1183: 10 | G1183: 3350 | H1183: 25.1 | I1183: 25091.5 | J1183: Cancelled | K1183: Chennai | L1183: =PROPER(TRIM(K1183)) -> Chennai | M1183: =_xlfn.XLOOKUP(D1183, Products!A:A, Products!C:C) -> Beauty | N1183: =_xlfn.XLOOKUP(E9, Sales_Reps!A:A, Sales_Reps!C:C) -> East | O1183: =_xlfn.XLOOKUP(D1183, Products!A:A, Products!D:D) -> 1728 | P1183: =_xlfn.XLOOKUP(D1183, Products!A:A, Products!E:E) -> 3350
A1184: ORD-01183 | B1184: 45307 | C1184: CUST-0138 | D1184: PROD-059 | E1184: R025 | F1184: 3 | G1184: 3780 | H1184: 3.8 | I1184: 10909.08 | J1184: Completed | K1184: Chennai | L1184: =PROPER(TRIM(K1184)) -> Chennai | M1184: =_xlfn.XLOOKUP(D1184, Products!A:A, Products!C:C) -> Sports | N1184: =_xlfn.XLOOKUP(E10, Sales_Reps!A:A, Sales_Reps!C:C) -> North | O1184: =_xlfn.XLOOKUP(D1184, Products!A:A, Products!D:D) -> 1860 | P1184: =_xlfn.XLOOKUP(D1184, Products!A:A, Products!E:E) -> 3780
A1185: ORD-01184 | B1185: 45651 | C1185: CUST-0157 | D1185: PROD-003 | E1185: R008 | F1185: 4 | G1185: 3570 | H1185: 0.9 | I1185: 14151.48 | J1185: Pending | K1185: Pune | L1185: =PROPER(TRIM(K1185)) -> Pune | M1185: =_xlfn.XLOOKUP(D1185, Products!A:A, Products!C:C) -> Electronics | N1185: =_xlfn.XLOOKUP(E11, Sales_Reps!A:A, Sales_Reps!C:C) -> West | O1185: =_xlfn.XLOOKUP(D1185, Products!A:A, Products!D:D) -> 1665 | P1185: =_xlfn.XLOOKUP(D1185, Products!A:A, Products!E:E) -> 3570
A1186: ORD-01185 | B1186: 45436 | C1186: CUST-0298 | D1186: PROD-055 | E1186: R024 | F1186: 5 | G1186: 2860 | H1186: 20.1 | I1186: 11425.7 | J1186: Completed | K1186: Delhi | L1186: =PROPER(TRIM(K1186)) -> Delhi | M1186: =_xlfn.XLOOKUP(D1186, Products!A:A, Products!C:C) -> Sports | N1186: =_xlfn.XLOOKUP(E12, Sales_Reps!A:A, Sales_Reps!C:C) -> South | O1186: =_xlfn.XLOOKUP(D1186, Products!A:A, Products!D:D) -> 2028 | P1186: =_xlfn.XLOOKUP(D1186, Products!A:A, Products!E:E) -> 2860
A1187: ORD-01186 | B1187: 45518 | C1187: CUST-0132 | D1187: PROD-016 | E1187: R003 | F1187: 1 | G1187: 620 | H1187: 1.1 | I1187: 613.18 | J1187: Cancelled | K1187: Delhi | L1187: =PROPER(TRIM(K1187)) -> Delhi | M1187: =_xlfn.XLOOKUP(D1187, Products!A:A, Products!C:C) -> Apparel | N1187: =_xlfn.XLOOKUP(E13, Sales_Reps!A:A, Sales_Reps!C:C) -> West | O1187: =_xlfn.XLOOKUP(D1187, Products!A:A, Products!D:D) -> 396 | P1187: =_xlfn.XLOOKUP(D1187, Products!A:A, Products!E:E) -> 620
... A2001: ORD-02000 | B2001: 45325 | C2001: CUST-0238 | D2001: PROD-034 | E2001: R023 | F2001: 6 | G2001: 5080 | H2001: 28.1 | I2001: 21915.12 | J2001: Completed | K2001: Delhi | L2001: =PROPER(TRIM(K2001)) -> Delhi | M2001: =_xlfn.XLOOKUP(D2001, Products!A:A, Products!C:C) -> Home | N2001: =_xlfn.XLOOKUP(E827, Sales_Reps!A:A, Sales_Reps!C:C) -> West | O2001: =_xlfn.XLOOKUP(D2001, Products!A:A, Products!D:D) -> 2459 | P2001: =_xlfn.XLOOKUP(D2001, Products!A:A, Products!E:E) -> 5080

Sheet Customers
A1: customer_id | B1: customer_name | C1: age | D1: city | E1: segment | F1: signup_date
A2: CUST-0001 | B2: Amit Agarwal | C2: 36 | D2: Pune | E2: Retail | F2: 44819
A3: CUST-0002 | B3: Vihaan Malhotra | C3: 42 | D3: Pune | E3: Corporate | F3: 44984
A4: CUST-0003 | B4: Navya Malhotra | C4: 33 | D4: Mumbai | E4: Retail | F4: 44059
A5: CUST-0004 | B5: Aaradhya Mehta | C5: 53 | D5: delhi | E5: Retail | F5: 44054
A6: CUST-0005 | B6: Myra Malhotra | C6: 52 | D6: Chennai | E6: Corporate | F6: 45037
A7: CUST-0006 | B7: Shaurya Iyer | C7: 44 | D7: Pune | E7: SMB | F7: 44302
A8: CUST-0007 | B8: Dhruv Joshi | C8: 47 | D8: Bengaluru | E8: Retail | F8: 44498
A9: CUST-0008 | B9: Kavita Malhotra | C9: 39 | D9: Pune | E9: SMB | F9: 45162
A10: CUST-0009 | B10: Neha Malhotra | C10: 61 | D10: Mumbai | E10: Retail | F10: 44343
A11: CUST-0010 | B11: Aaradhya Gupta | C11: 61 | D11: Mumbai | E11: SMB | F11: 44975
A12: CUST-0011 | B12: Diya Menon | C12: 41 | D12: Chennai | E12: Corporate | F12: 44821
A13: CUST-0012 | B13: Prisha Desai | C13: 43 | D13: Pune | E13: Retail | F13: 44718
... A301: CUST-0300 | B301: Rohit Nair | C301: 38 | D301: Mumbai | E301: Retail | F301: 43932

Sheet Products
A1: product_id | B1: product_name | C1: category | D1: unit_cost | E1: unit_price | F1: is_active
A2: PROD-001 | B2: Smartphone Pro | C2: Electronics | D2: 2405 | E2: 5330 | F2: TRUE
A3: PROD-002 | B3: Wireless Earbuds | C3: Electronics | D3: 1052 | E3: 2600 | F3: TRUE
A4: PROD-003 | B4: Smart Watch | C4: Electronics | D4: 1665 | E4: 3570 | F4: TRUE
A5: PROD-004 | B5: Laptop Bag | C5: Electronics | D5: 1559 | E5: 3870 | F5: TRUE
A6: PROD-005 | B6: Power Bank | C6: Electronics | D6: 128 | E6: 300 | F6: TRUE
A7: PROD-006 | B7: Bluetooth Speaker | C7: Electronics | D7: 2865 | E7: 3970 | F7: TRUE
A8: PROD-007 | B8: USB-C Cable | C8: Electronics | D8: 861 | E8: 1430 | F8: TRUE
A9: PROD-008 | B9: Wireless Mouse | C9: Electronics | D9: 1259 | E9: 2660 | F9: FALSE
A10: PROD-009 | B10: Mechanical Keyboard | C10: Electronics | D10: 517 | E10: 1220 | F10: TRUE
A11: PROD-010 | B11: Tablet Stand | C11: Electronics | D11: 1149 | E11: 2640 | F11: TRUE
A12: PROD-011 | B12: Cotton T-Shirt | C12: Apparel | D12: 1748 | E12: 3450 | F12: TRUE
A13: PROD-012 | B13: Denim Jeans | C13: Apparel | D13: 1886 | E13: 3160 | F13: TRUE
... A61: PROD-060 | B61: Gym Gloves | C61: Sports | D61: 147 | E61: 190 | F61: TRUE

Sheet Sales_Reps
A1: rep_id | B1: rep_name | C1: region | D1: hire_date | E1: team_lead_id
A2: R001 | B2: Rajesh Malhotra | C2: North | D2: 44207
A3: R002 | B3: Sunita Malhotra | C3: North | D3: 44028
A4: R003 | B4: Amit Singh | C4: North | D4: 43651
A5: R004 | B5: Priya Singh | C5: North | D5: 44907
A6: R005 | B6: Vikram Patel | C6: North | D6: 43588 | E6: R001
A7: R006 | B7: Neha Desai | C7: North | D7: 44131 | E7: R001
A8: R007 | B8: Suresh Menon | C8: North | D8: 43493 | E8: R001
A9: R008 | B9: Kavita Patel | C9: North | D9: 44693 | E9: R001
A10: R009 | B10: Manoj Patel | C10: South | D10: 44804 | E10: R002
A11: R010 | B11: Divya Rao | C11: South | D11: 43904 | E11: R002
A12: R011 | B12: Anil Verma | C12: South | D12: 44622 | E12: R002
A13: R012 | B13: Pooja Nair | C13: South | D13: 44890 | E13: R002
A14: R013 | B14: Sanjay Kapoor | C14: South | D14: 45215 | E14: R002
A15: R014 | B15: Ritu Menon | C15: South | D15: 44469 | E15: R002
A16: R015 | B16: Deepak Shah | C16: South | D16: 45231 | E16: R002
A17: R016 | B17: Anjali Chopra | C17: South | D17: 43614 | E17: R002
... A31: R030 | B31: Kiran Bhatt | C31: West | D31: 44506 | E31: R004

Sheet Targets
A1: rep_id | B1: Jan-24 | C1: Feb-24 | D1: Mar-24 | E1: Apr-24 | F1: May-24 | G1: Jun-24 | H1: Jul-24 | I1: Aug-24 | J1: Sep-24 | K1: Oct-24 | L1: Nov-24 | M1: Dec-24
A2: R001 | B2: 231324 | C2: 171682 | D2: 234376 | E2: 326967 | F2: 350588 | G2: 385324 | H2: 307980 | I2: 327947 | J2: 181016 | K2: 374039 | L2: 212805 | M2: 405999
A3: R002 | B3: 438126 | C3: 346266 | D3: 329993 | E3: 370744 | F3: 294660 | G3: 341556 | H3: 151934 | I3: 223794 | J3: 438641 | K3: 344308 | L3: 296172 | M3: 304288
A4: R003 | B4: 358703 | C4: 320519 | D4: 327321 | E4: 298753 | F4: 254636 | G4: 351929 | H4: 264723 | I4: 216459 | J4: 391945 | K4: 362426 | L4: 289199 | M4: 301863
A5: R004 | B5: 389594 | C5: 376422 | D5: 324156 | E5: 420255 | F5: 409107 | G5: 269954 | H5: 179097 | I5: 370568 | J5: 387395 | K5: 243454 | L5: 232530 | M5: 201999
A6: R005 | B6: 436862 | C6: 391158 | D6: 340224 | E6: 170548 | F6: 229390 | G6: 349525 | H6: 154683 | I6: 320848 | J6: 354452 | K6: 377180 | L6: 342347 | M6: 183362
A7: R006 | B7: 348734 | C7: 358191 | D7: 250385 | E7: 219657 | F7: 249365 | G7: 435704 | H7: 260892 | I7: 250741 | J7: 358402 | K7: 379858 | L7: 213280 | M7: 224634
A8: R007 | B8: 280057 | C8: 330342 | D8: 336856 | E8: 227425 | F8: 233647 | G8: 307088 | H8: 370724 | I8: 440008 | J8: 406347 | K8: 217357 | L8: 299289 | M8: 214568
A9: R008 | B9: 252886 | C9: 206057 | D9: 318209 | E9: 411230 | F9: 448660 | G9: 171135 | H9: 305339 | I9: 432264 | J9: 294273 | K9: 371409 | L9: 284207 | M9: 437068
A10: R009 | B10: 268752 | C10: 393256 | D10: 310649 | E10: 246237 | F10: 271287 | G10: 314545 | H10: 406506 | I10: 334930 | J10: 348625 | K10: 408928 | L10: 243749 | M10: 418409
A11: R010 | B11: 384734 | C11: 156698 | D11: 283679 | E11: 276085 | F11: 409270 | G11: 285230 | H11: 304233 | I11: 178221 | J11: 284216 | K11: 287373 | L11: 229082 | M11: 298969
A12: R011 | B12: 186029 | C12: 151419 | D12: 253251 | E12: 379757 | F12: 204209 | G12: 179396 | H12: 378008 | I12: 182649 | J12: 267772 | K12: 350352 | L12: 358042 | M12: 359960
A13: R012 | B13: 352158 | C13: 251181 | D13: 321255 | E13: 300863 | F13: 241731 | G13: 393275 | H13: 313561 | I13: 283604 | J13: 429065 | K13: 194420 | L13: 254168 | M13: 389283
... A31: R030 | B31: 151584 | C31: 221679 | D31: 385157 | E31: 290386 | F31: 236041 | G31: 407985 | H31: 184446 | I31: 342894 | J31: 180344 | K31: 292917 | L31: 314858 | M31: 364057

Sheet Q1_Lookups
A1: Q1 - LOOKUP FUNCTIONS (25 marks total)
A2: VLOOKUP · INDEX-MATCH · Two-way lookup · Chain lookup · Approximate lookup · Self-join
A4: Q# | B4: Question | C4: Marks | D4: Hint | E4: Your Answer | F4: Format
A5: Q1.1 | B5: For order ORD-00234, what is the customer_id? | C5: 3 | D5: Simple VLOOKUP on Orders sheet. | E5: =_xlfn.XLOOKUP("ORD-00234", Orders!A:A, Orders!C:C) -> CUST-0173 | F5: CUST-####
A6: Q1.2 | B6: For order ORD-00456, what is the product_name? (You will need to look up the product_id first, then find its name in Products.) | C6: 3 | D6: Two-step lookup, or nested VLOOKUP. | E6: =_xlfn.XLOOKUP(_xlfn.XLOOKUP("ORD-00456", Orders!A:A, Orders!D:D), Products!A:A, Products!B:B) -> Dumbbells 5kg | F6: Text
A7: Q1.3 | B7: For order ORD-00987, what is the rep_name of the sales rep? Note: the rep_name is in a column that appears to the LEFT of what you might look up first. | C7: 3 | D7: VLOOKUP has directional limits - INDEX/MATCH does not. | E7: =_xlfn.XLOOKUP(_xlfn.XLOOKUP("ORD-00987", Orders!A:A, Orders!E:E), Sales_Reps!A:A, Sales_Reps!B:B) -> Nisha Menon | F7: Text
A8: Q1.4 | B8: From the Targets sheet, what is the target value for rep R012 in the month Mar-24? | C8: 4 | D8: Two-way lookup: row = rep_id, column = month. | E8: =INDEX(Targets!B2:M100, MATCH("R012", Targets!A2:A100, 0), MATCH("Mar-24", Targets!B1:M1, 0)) -> 321255 | F8: Whole number
A9: Q1.5 | B9: For order ORD-01500, what is the CATEGORY of the product ordered? (Chain: order → product_id → category) | C9: 4 | D9: Multi-hop lookup across sheets. | E9: =_xlfn.XLOOKUP(_xlfn.XLOOKUP("ORD-01500", Orders!A:A, Orders!D:D), Products!A:A, Products!C:C) -> Electronics | F9: Text
A10: Q1.6 | B10: For order ORD-00789, which DISCOUNT SLAB does it fall in? Use the slab table below (rows 20-24). Slab breakpoints are the LOWER bound of each range. | C10: 3 | D10: Approximate-match VLOOKUP (sort ascending, TRUE / omit last arg). | E10: =_xlfn.XLOOKUP(_xlfn.XLOOKUP("ORD-00789", Orders!A:A, Orders!H:H), B17:B20, C17:C20, "", -1) -> Bronze | F10: Text
A11: Q1.7 | B11: For order ORD-01234, in one cell produce the string: "<rep_name> (<sales_region>)" - e.g. "Amit Singh (South)". | C11: 3 | D11: Two lookups joined with & or CONCATENATE. | E11: =_xlfn.XLOOKUP(_xlfn.XLOOKUP("ORD-01234", Orders!A:A, Orders!E:E), Sales_Reps!A:A, Sales_Reps!B:B) & " (" & _xlfn.XLOOKUP(_xlfn.XLOOKUP("ORD-01234", Orders!A:A, Orders!E:E), Sales_Reps!A:A, Sales_Reps!C:C) & ")" -> Sanjay Kapoor (South) | F11: Text
A12: Q1.8 | B12: What is the rep_name of the TEAM LEAD for rep R017? (The Sales_Reps sheet has team_lead_id - you need to self-join to find that person's name.) | C12: 2 | D12: Look up the team_lead_id, then look up THAT id's rep_name. | E12: =_xlfn.XLOOKUP(_xlfn.XLOOKUP("R017", Sales_Reps!A:A, Sales_Reps!E:E), Sales_Reps!A:A, Sales_Reps!B:B) -> Amit Singh | F12: Text
B15: DISCOUNT SLAB REFERENCE TABLE (use for Q1.6)
B17: Discount % (Lower) | C17: Slab
B18: 0 | C18: Bronze
B19: 5 | C19: Silver
B20: 15 | C20: Gold
B21: 25 | C21: Platinum

Sheet Q2_Cleaning
A1: Q2 - DATA CLEANING & QUALITY DIAGNOSTICS (20 marks total)
A2: Duplicates · Whitespace · Case Inconsistency · Referential Integrity · Discontinued SKUs · Anomaly Patterns
A4: Q# | B4: Question | C4: Marks | D4: Hint | E4: Your Answer | F4: Format
A5: Q2.1 | B5: How many DUPLICATE rows exist in the Orders sheet (i.e., how many order_id values appear more than once)? Count each duplicate as ONE (not the extras). | C5: 3 | D5: COUNTIF > 1, then count. Watch what you're counting - rows or IDs. | E5: {=SUM(--(COUNTIF(Orders!A2:A10000, _xlfn.UNIQUE(Orders!A2:A10000))>1))} -> 20 | F5: Whole number
A6: Q2.2 | B6: How many customers in the Customers sheet have LEADING or TRAILING whitespace in their customer_name? | C6: 3 | D6: Compare LEN vs LEN(TRIM). Or use SUMPRODUCT with a boolean. | E6: {=SUMPRODUCT(--(LEN(Customers!B2:B1000)<>LEN(TRIM(Customers!B2:B1000))))} -> 15 | F6: Whole number
A7: Q2.3 | B7: The Customers sheet has some cities in inconsistent case (e.g., "mumbai", "MUMBAI", "Mumbai"). How many DISTINCT cities exist AFTER standardizing case? | C7: 3 | D7: Combine PROPER/UPPER with a de-dup count. SUMPRODUCT + 1/COUNTIF trick works. | E7: {=COUNTA(_xlfn.UNIQUE(PROPER(TRIM(Customers!D2:D1000))))} -> 7 | F7: Whole number
A8: Q2.4 | B8: How many orders reference a customer_id that DOES NOT EXIST in the Customers sheet? (Broken foreign key) | C8: 4 | D8: Use MATCH with ISNA/ISERROR, then count. | E8: {=SUMPRODUCT(--ISNA(MATCH(Orders!C2:C10000, Customers!A:A, 0)))} -> 8029 | F8: Whole number
A9: Q2.5 | B9: How many orders reference a product that is currently DISCONTINUED (is_active = FALSE in the Products sheet)? | C9: 3 | D9: VLOOKUP the is_active flag, then count where FALSE. | E9: =_xlfn.XLOOKUP(D2, Products!A:A, Products!F:F) -> 0 | F9: Whole number
A10: Q2.6 | B10: Find the "suspicious pattern": how many orders have payment_status = "Cancelled" AND a discount_pct > 20%? (This pattern often indicates promo abuse - a real-world diagnostic query.) | C10: 4 | D10: COUNTIFS with two criteria. | E10: =COUNTIFS(Orders!J:J, "Cancelled", Orders!H:H, ">20") -> 58 | F10: Whole number

Sheet Q3_Aggregation
A1: Q3 - CONDITIONAL AGGREGATION (25 marks total)
A2: SUMIFS · COUNTIFS · AVERAGEIFS · Nested IF logic · Multi-sheet aggregation · Top-N logic
A4: Q# | B4: Question | C4: Marks | D4: Hint | E4: Your Answer | F4: Format
A5: Q3.1 | B5: What is the TOTAL REVENUE (sum of final_amount) for orders in Q3 2024 (Jul-Sep) where ship_city is Mumbai? | C5: 4 | D5: SUMIFS with 3 conditions: date >= start, date <= end, city = Mumbai. Beware case issues. | E5: {=SUM(_xlfn._xlws.FILTER(Orders!I2:I10000, (Orders!B2:B10000>=DATE(2024,7,1)) * (Orders!B2:B10000<=DATE(2024,9,30)) * (PROPER(TRIM(Orders!K2:K10000))="Mumbai"), 0))} -> 1217239 | F5: Currency
A6: Q3.2 | B6: How many orders have discount_pct > 15% AND payment_status = "Completed"? | C6: 3 | D6: COUNTIFS with two conditions. | E6: =COUNTIFS(Orders!H:H, ">15", Orders!J:J, "Completed") -> 723 | F6: Whole number
A7: Q3.3 | B7: What is the AVERAGE final_amount for orders where the product CATEGORY is "Electronics" AND the customer SEGMENT is "Corporate"? Note: Both fields come from OTHER sheets - you'll need helper columns. | C7: 5 | D7: Helper columns in Orders: VLOOKUP category from Products, VLOOKUP segment from Customers. Then AVERAGEIFS. | E7: {=AVERAGE(_xlfn._xlws.FILTER(Orders!I2:I10000, (_xlfn.XLOOKUP(Orders!D2:D10000, Products!A:A, Products!C:C, "")="Electronics") * (_xlfn.XLOOKUP(Orders!C2:C10000, Customers!A:A, Customers!E:E, "")="Corporate")))} -> 13981.402 | F7: Currency
A8: Q3.4 | B8: What is the COMBINED REVENUE of the TOP 3 reps by total revenue? (Sum of the 3 highest rep totals.) | C8: 4 | D8: Compute per-rep totals, then use SUMPRODUCT with LARGE, or sort and sum top 3. | E8: {=SUM(LARGE(SUMIFS(Orders!I:I, Orders!E:E, _xlfn.UNIQUE(_xlfn._xlws.FILTER(Orders!E2:E10000, Orders!E2:E10000<>""))), {1,2,3}))} -> 3342678.5 | F8: Currency
A9: Q3.5 | B9: For rep R015 in Nov-24: compute the actual revenue and compare to the target (from Targets sheet). Report the PERFORMANCE TIER using: <80% → "Below", 80-120% → "On Track", >120% → "Exceeds". Return only the tier text. | C9: 5 | D9: Nested IF (or IFS): compute actual/target ratio, then classify. | E9: {=_xlfn.LET(_xlpm.actual, SUMIFS(Orders!I:I, Orders!E:E, "R015", Orders!B:B, ">=11/1/2024", Orders!B:B, "<=11/30/2024"), _xlpm.target, INDEX(Targets!B2:M100, MATCH("R015", Targets!A2:A100, 0), MATCH("Nov-24", Targets!B1:M1, 0)), _xlpm.ratio, _xlpm.actual/_xlpm.target, _xlfn.IFS(_xlpm.ratio<0.8, "Below", _xlpm.ratio<=1.2, "On Track", _xlpm.ratio>1.2, "Exceeds"))} -> Below | F9: Text
A10: Q3.6 | B10: What is the TOTAL revenue from Corporate segment customers aged between 30 and 40 (both inclusive)? | C10: 4 | D10: Helper columns for age and segment. Then SUMIFS with numeric range. | E10: {=SUM(_xlfn._xlws.FILTER(Orders!I2:I10000, (_xlfn.XLOOKUP(Orders!C2:C10000, Customers!A:A, Customers!E:E, "")="Corporate") * (_xlfn.XLOOKUP(Orders!C2:C10000, Customers!A:A, Customers!C:C, 0)>=30) * (_xlfn.XLOOKUP(Orders!C2:C10000, Customers!A:A, Customers!C:C, 0)<=40), 0))} -> 982568.4 | F10: Currency

Sheet Q4_Pivot
A1: Q4 - PIVOT TABLES (20 marks total)
A2: 2D Pivots · Filters · % of Row Total · Date Grouping · Calculated Fields · Cross-Sheet Data
A4: Q# | B4: Question | C4: Marks | D4: Hint | E4: Your Answer | F4: Format
A5: Q4.1 | B5: Build a pivot with sales_region as rows and product category as columns, values = SUM of final_amount. What value appears at the intersection of "South" and "Electronics"? | C5: 4 | D5: You need to add category (from Products) and region (from Sales_Reps) as columns to Orders first. Insert PivotTable from combined data. | E5: 1453231.8 | F5: Currency
A6: Q4.2 | B6: Build a pivot: rows = order month (Jan-24 through Dec-24), columns = sales_rep_id, values = SUM of final_amount. What is the HIGHEST single value in the entire pivot? (One number.) | C6: 4 | D6: After building, use MAX() over the pivot data range, or scan visually. | E6: 216421.52 | F6: Currency
A7: Q4.3 | B7: For the North sales_region only: what PERCENTAGE of total revenue comes from the Apparel category? Configure the pivot with Show Values As → % of Row Total. | C7: 4 | D7: Pivot: rows=region, cols=category, values=sum(final_amount), Show Values As = % of Row Total. | E7: 0.13815372 | F7: Percentage
A8: Q4.4 | B8: Group order dates by QUARTER in a pivot. What is the total revenue for Q4 2024 (Oct-Dec)? | C8: 4 | D8: PivotTable → Group By → Quarter. Or SUMIFS with date range. | E8: 6459443 | F8: Currency
A9: Q4.5 | B9: Create a CALCULATED FIELD in the pivot: profit_margin = (unit_price - unit_cost) / unit_price. What is the AVERAGE profit_margin for orders shipped to Delhi? Give as a percentage. | C9: 4 | D9: Add unit_cost via VLOOKUP as helper column. Create pivot calculated field, filter to Delhi. | E9: 0.449 | F9: Percentage

Sheet Q5_Advanced
A1: Q5 - ADVANCED (10 marks total)
A2: RANK · Running Totals · TEXTJOIN · LARGE + INDEX/MATCH · Multi-condition top-N
A4: Q# | B4: Question | C4: Marks | D4: Hint | E4: Your Answer | F4: Format
A5: Q5.1 | B5: Rank all sales reps by total revenue (highest = rank 1). Who (name) is at RANK #7? | C5: 2 | D5: Per-rep totals, then use RANK.EQ, or sort. Return the rep_name at position 7. | E5: {=_xlfn.LET(_xlpm.reps, _xlfn.UNIQUE(Orders!E2:E10000), _xlpm.revs, SUMIFS(Orders!I2:I10000, Orders!E2:E10000, _xlpm.reps), _xlpm.sorted, _xlfn.SORTBY(_xlpm.reps, _xlpm.revs, -1), _xlfn.XLOOKUP(INDEX(_xlpm.sorted, 7), Sales_Reps!A:A, Sales_Reps!B:B))} -> Amit Singh | F5: Text
A6: Q5.2 | B6: What is the CUMULATIVE revenue from Jan 2024 through the end of Aug 2024? (Sum of final_amount where order_date <= 31-Aug-2024.) | C6: 2 | D6: SUMIFS with date <=. | E6: =SUMIFS(Orders!I:I, Orders!B:B, "<=" & DATE(2024, 8, 31)) -> 18050690 | F6: Currency
A7: Q5.3 | B7: Among orders where the sales rep is in the WEST region: which product (by name) has the 2nd highest total revenue? | C7: 3 | D7: Helper: sales_region on orders. Filter/pivot to West, sum by product, rank, get #2, VLOOKUP product name. | E7: {=_xlfn.LET(_xlpm.prods, _xlfn.UNIQUE(Orders!D2:D10000), _xlpm.revs, _xlfn.MAP(_xlpm.prods, _xlfn.LAMBDA(_xlpm.p, SUM(_xlfn._xlws.FILTER(Orders!I2:I10000, (Orders!D2:D10000=_xlpm.p) * (_xlfn.XLOOKUP(Orders!E2:E10000, Sales_Reps!A:A, Sales_Reps!C:C)="West"), 0)))), _xlpm.sorted, _xlfn.SORTBY(_xlpm.prods, _xlpm.revs, -1), _xlfn.XLOOKUP(INDEX(_xlpm.sorted, 2), Products!A:A, Products!B:B))} -> Smart Watch | F7: Text
A8: Q5.4 | B8: Concatenate the names of the top 5 reps by revenue into a single cell, separated by " | " (space-pipe-space). | C8: 2 | D8: TEXTJOIN with delimiter " | ". Combine with LARGE to pull top 5. | E8: {=_xlfn.LET(_xlpm.reps, _xlfn.UNIQUE(Orders!E2:E10000), _xlpm.revs, SUMIFS(Orders!I2:I10000, Orders!E2:E10000, _xlpm.reps), _xlpm.sorted_reps, _xlfn.SORTBY(_xlpm.reps, _xlpm.revs, -1), _xlpm.top_5_ids, _xlfn.TAKE(_xlpm.sorted_reps, 5), _xlpm.top_5_names, _xlfn.XLOOKUP(_xlpm.top_5_ids, Sales_Reps!A:A, Sales_Reps!B:B), _xlfn.TEXTJOIN(" | ", TRUE, _xlpm.top_5_names))} -> Neha Desai | Shalini Patel | Deepak Shah | Nisha Menon | Arun Iyer | F8: Text
A9: Q5.5 | B9: What is the HIGHEST single order value (final_amount) where ship_city = "Bengaluru" AND the product's category = "Grocery"? | C9: 1 | D9: MAXIFS with a category helper column, or nested MAX(IF()). | E9: {=MAX(_xlfn._xlws.FILTER(Orders!I2:I10000, (PROPER(TRIM(Orders!K2:K10000))="Bengaluru") * (_xlfn.XLOOKUP(Orders!D2:D10000, Products!A:A, Products!C:C)="Grocery"), 0))} -> 22134 | F9: Currency
